faker_clickstream/__init__.py
faker_clickstream/clickstream.py
faker_clickstream/event_constants.py
faker_clickstream/ip.py
faker_clickstream/mobile_phones.py
faker_clickstream/user_agents.py
faker_clickstream-0.1.1.dist-info/LICENSE
faker_clickstream-0.1.1.dist-info/METADATA
faker_clickstream-0.1.1.dist-info/WHEEL
faker_clickstream-0.1.1.dist-info/top_level.txt
faker_clickstream-0.1.1.dist-info/zip-safe
faker_clickstream-0.1.1.dist-info/RECORD
