Metadata-Version: 2.1
Name: faker-clickstream
Version: 0.1.1
Summary: Clickstream Faker Provider for Python.
Home-page: https://github.com/cnatsis/faker-clickstream
Author: Christos Natsis
Author-email: christos_na@hotmail.com
License: Apache License, Version 2.0
Project-URL: Issues Tracker, https://github.com/cnatsis/faker-clickstream/issues
Platform: UNKNOWN
Classifier: Programming Language :: Python :: 3
Classifier: Programming Language :: Python :: 3.6
Classifier: Programming Language :: Python :: 3.8
Classifier: License :: OSI Approved :: Apache Software License
Classifier: Operating System :: OS Independent
Classifier: Topic :: Software Development :: Libraries :: Python Modules
Classifier: Topic :: Utilities
Requires-Python: >=3.6
License-File: LICENSE
Requires-Dist: Faker
